Metadata-Version: 2.1
Name: socorepo
Version: 1.2.1
Summary: A webapp that fetches software version listings and presents them as download sites.
Home-page: https://github.com/LoadingByte/socorepo
Author: LoadingByte
Author-email: hello@loadingbyte.com
License: MIT
Platform: UNKNOWN
Classifier: Development Status :: 5 - Production/Stable
Classifier: Environment :: Web Environment
Classifier: Intended Audience :: Developers
Classifier: Intended Audience :: System Administrators
Classifier: License :: OSI Approved :: MIT License
Classifier: Natural Language :: English
Classifier: Operating System :: OS Independent
Classifier: Programming Language :: Python :: 3
Classifier: Topic :: Internet
Requires-Python: >=3.7
License-File: LICENSE
Requires-Dist: toml
Requires-Dist: requests
Requires-Dist: Flask
Requires-Dist: Flask-WTF
